<?xml version="1.0" encoding="utf-8" ?><dwsync><file name="Resourceviews.php" server="oa2019.tk//var/www/oa2019/" local="3485876873" remote="318763443878773385" Dst="-1" /><file name="Storage.php" server="oa2019.tk//var/www/oa2019/" local="3485876873" remote="318763443878773385" Dst="-1" /><file name="Books.php" server="oa2019.tk//var/www/oa2019/" local="3485876873" remote="318763443878773385" Dst="-1" /><file name="Calendar.php" server="oa2019.tk//var/www/oa2019/" local="3485876873" remote="318763443878773385" Dst="-1" /><file name="AndroidPublisher.php" server="oa2019.tk//var/www/oa2019/" local="3485876873" remote="318763443878773385" Dst="-1" /><file name="GamesManagement.php" server="oa2019.tk//var/www/oa2019/" local="3485876873" remote="318763443878773385" Dst="-1" /><file name="SQLAdmin.php" server="oa2019.tk//var/www/oa2019/" local="3485876873" remote="318763443878773385" Dst="-1" /><file name="GroupsMigration.php" server="oa2019.tk//var/www/oa2019/" local="3485876873" remote="318763443878773385" Dst="-1" /><file name="Freebase.php" server="oa2019.tk//var/www/oa2019/" local="3485876873" remote="318763443878773385" Dst="-1" /><file name="Reseller.php" server="oa2019.tk//var/www/oa2019/" local="3485876873" remote="318763443878773385" Dst="-1" /><file name="Directory.php" server="oa2019.tk//var/www/oa2019/" local="3485876873" remote="318763443878773385" Dst="-1" /><file name="PlusDomains.php" server="oa2019.tk//var/www/oa2019/" local="3485876873" remote="318763443878773385" Dst="-1" /><file name="YouTubeAnalytics.php" server="oa2019.tk//var/www/oa2019/" local="3485876873" remote="318763443878773385" Dst="-1" /><file name="AdExchangeBuyer.php" server="oa2019.tk//var/www/oa2019/" local="3485876873" remote="318763443878773385" Dst="-1" /><file name="IdentityToolkit.php" server="oa2019.tk//var/www/oa2019/" local="3485876873" remote="318763443878773385" Dst="-1" /><file name="Tasks.php" server="oa2019.tk//var/www/oa2019/" local="3485876873" remote="318763443878773385" Dst="-1" /><file name="Customsearch.php" server="oa2019.tk//var/www/oa2019/" local="3485876873" remote="318763443878773385" Dst="-1" /><file name="MapsEngine.php" server="oa2019.tk//var/www/oa2019/" local="3485876873" remote="318763443878773385" Dst="-1" /><file name="Prediction.php" server="oa2019.tk//var/www/oa2019/" local="3485876873" remote="318763443878773385" Dst="-1" /><file name="AdSense.php" server="oa2019.tk//var/www/oa2019/" local="3485876873" remote="318763443878773385" Dst="-1" /><file name="Licensing.php" server="oa2019.tk//var/www/oa2019/" local="3485876873" remote="318763443878773385" Dst="-1" /><file name="Doubleclicksearch.php" server="oa2019.tk//var/www/oa2019/" local="3485876873" remote="318763443878773385" Dst="-1" /><file name="Bigquery.php" server="oa2019.tk//var/www/oa2019/" local="3485876873" remote="318763443878773385" Dst="-1" /><file name="AdExchangeSeller.php" server="oa2019.tk//var/www/oa2019/" local="3485876873" remote="318763443878773385" Dst="-1" /><file name="Compute.php" server="oa2019.tk//var/www/oa2019/" local="3485876873" remote="318763443878773385" Dst="-1" /><file name="CivicInfo.php" server="oa2019.tk//var/www/oa2019/" local="3485876873" remote="318763443878773385" Dst="-1" /><file name="Resource.php" server="oa2019.tk//var/www/oa2019/" local="3485877417" remote="318763443878773978" Dst="-1" /><file name="Drive.php" server="oa2019.tk//var/www/oa2019/" local="3485876873" remote="318763443878773385" Dst="-1" /><file name="Admin.php" server="oa2019.tk//var/www/oa2019/" local="3485876873" remote="318763443878773385" Dst="-1" /><file name="Oauth2.php" server="oa2019.tk//var/www/oa2019/" local="3485876873" remote="318763443878773385" Dst="-1" /><file name="Orkut.php" server="oa2019.tk//var/www/oa2019/" local="3485876873" remote="318763443878773385" Dst="-1" /><file name="SiteVerification.php" server="oa2019.tk//var/www/oa2019/" local="3485876873" remote="318763443878773385" Dst="-1" /><file name="Pagespeedonline.php" server="oa2019.tk//var/www/oa2019/" local="3485876873" remote="318763443878773385" Dst="-1" /><file name="Groupssettings.php" server="oa2019.tk//var/www/oa2019/" local="3485876873" remote="318763443878773385" Dst="-1" /><file name="Reports.php" server="oa2019.tk//var/www/oa2019/" local="3485876873" remote="318763443878773385" Dst="-1" /><file name="AppState.php" server="oa2019.tk//var/www/oa2019/" local="3485876873" remote="318763443878773385" Dst="-1" /><file name="Analytics.php" server="oa2019.tk//var/www/oa2019/" local="3485876873" remote="318763443878773385" Dst="-1" /><file name="Coordinate.php" server="oa2019.tk//var/www/oa2019/" local="3485876873" remote="318763443878773385" Dst="-1" /><file name="AdSenseHost.php" server="oa2019.tk//var/www/oa2019/" local="3485876873" remote="318763443878773385" Dst="-1" /><file name="Dfareporting.php" server="oa2019.tk//var/www/oa2019/" local="3485876873" remote="318763443878773385" Dst="-1" /><file name="Taskqueue.php" server="oa2019.tk//var/www/oa2019/" local="3485876873" remote="318763443878773385" Dst="-1" /><file name="Games.php" server="oa2019.tk//var/www/oa2019/" local="3485876873" remote="318763443878773385" Dst="-1" /><file name="Blogger.php" server="oa2019.tk//var/www/oa2019/" local="3485876873" remote="318763443878773385" Dst="-1" /><file name="Replicapool.php" server="oa2019.tk//var/www/oa2019/" local="3485876873" remote="318763443878773385" Dst="-1" /><file name="Dns.php" server="oa2019.tk//var/www/oa2019/" local="3485876873" remote="318763443878773385" Dst="-1" /><file name="Audit.php" server="oa2019.tk//var/www/oa2019/" local="3485876873" remote="318763443878773385" Dst="-1" /><file name="Webfonts.php" server="oa2019.tk//var/www/oa2019/" local="3485876873" remote="318763443878773385" Dst="-1" /><file name="DoubleClickBidManager.php" server="oa2019.tk//var/www/oa2019/" local="3485876873" remote="318763443878773385" Dst="-1" /><file name="Content.php" server="oa2019.tk//var/www/oa2019/" local="3485876873" remote="318763443878773385" Dst="-1" /><file name="QPXExpress.php" server="oa2019.tk//var/www/oa2019/" local="3485876873" remote="318763443878773385" Dst="-1" /><file name="Fusiontables.php" server="oa2019.tk//var/www/oa2019/" local="3485876873" remote="318763443878773385" Dst="-1" /><file name="Urlshortener.php" server="oa2019.tk//var/www/oa2019/" local="3485876873" remote="318763443878773385" Dst="-1" /><file name="Translate.php" server="oa2019.tk//var/www/oa2019/" local="3485876873" remote="318763443878773385" Dst="-1" /><file name="YouTube.php" server="oa2019.tk//var/www/oa2019/" local="3485876873" remote="318763443878773385" Dst="-1" /><file name="Manager.php" server="oa2019.tk//var/www/oa2019/" local="3485876873" remote="318763443878773385" Dst="-1" /><file name="Datastore.php" server="oa2019.tk//var/www/oa2019/" local="3485876873" remote="318763443878773385" Dst="-1" /><file name="Plus.php" server="oa2019.tk//var/www/oa2019/" local="3485876873" remote="318763443878773385" Dst="-1" /><file name="Mirror.php" server="oa2019.tk//var/www/oa2019/" local="3485876873" remote="318763443878773385" Dst="-1" /><file name="Exception.php" server="oa2019.tk//var/www/oa2019/" local="3485877417" remote="318763443878773977" Dst="-1" /><file name="Spectrum.php" server="oa2019.tk//var/www/oa2019/" local="3485876873" remote="318763443878773385" Dst="-1" /><file name="Genomics.php" server="oa2019.tk//var/www/oa2019/" local="3485876873" remote="318763443878773385" Dst="-1" /></dwsync>